duoreadme-0.0.1.dist-info/licenses/LICENSE
src/__init__.py
src/cli/__init__.py
src/cli/commands.py
src/cli/main.py
src/core/__init__.py
src/core/generator.py
src/core/parser.py
src/core/translator.py
src/data/__init__.py
src/data/default_config.yaml
src/models/__init__.py
src/models/types.py
src/services/__init__.py
src/services/sse_client.py
src/services/tencent_cloud.py
src/utils/__init__.py
src/utils/config.py
src/utils/file_utils.py
src/utils/json_extractor.py
src/utils/language_codes.py
src/utils/logger.py
duoreadme-0.0.1.dist-info/METADATA
duoreadme-0.0.1.dist-info/WHEEL
duoreadme-0.0.1.dist-info/entry_points.txt
duoreadme-0.0.1.dist-info/top_level.txt
duoreadme-0.0.1.dist-info/RECORD
