Metadata-Version: 2.4
Name: duoreadme
Version: 0.0.1
Summary: Auto Multilingual READMEs, Bridge Global Code.
Home-page: https://github.com/your-username/duoreadme
Author: timerring
Author-email: timerring <timerring@gmail.com>
Maintainer-email: timerring <timerring@gmail.com>
License: Apache-2.0
Project-URL: Homepage, https://github.com/duoreadme
Project-URL: Documentation, https://github.com/duoreadme/duoreadme
Project-URL: Repository, https://github.com/duoreadme/duoreadme
Project-URL: Bug Tracker, https://github.com/duoreadme/duoreadme/issues
Project-URL: Source Code, https://github.com/duoreadme/duoreadme
Keywords: readme,translation,multilingual,documentation,cli
Classifier: Development Status :: 4 - Beta
Classifier: Intended Audience :: Developers
Classifier: License :: OSI Approved :: Apache Software License
Classifier: Operating System :: OS Independent
Classifier: Programming Language :: Python :: 3
Classifier: Programming Language :: Python :: 3.8
Classifier: Programming Language :: Python :: 3.9
Classifier: Programming Language :: Python :: 3.10
Classifier: Programming Language :: Python :: 3.11
Classifier: Programming Language :: Python :: 3.12
Classifier: Topic :: Documentation
Classifier: Topic :: Software Development :: Documentation
Classifier: Topic :: Text Processing :: Linguistic
Requires-Python: >=3.8
License-File: LICENSE
Requires-Dist: bidict>=0.23.1
Requires-Dist: certifi>=2024.2.2
Requires-Dist: charset-normalizer>=3.3.2
Requires-Dist: h11>=0.14.0
Requires-Dist: netifaces>=0.10.6
Requires-Dist: python-engineio>=4.9.0
Requires-Dist: python-socketio>=5.11.4
Requires-Dist: requests>=2.31.0
Requires-Dist: simple-websocket>=1.0.0
Requires-Dist: socketio>=0.2.1
Requires-Dist: sseclient-py>=1.8.0
Requires-Dist: tencentcloud-sdk-python>=3.0.1224
Requires-Dist: websocket-client>=1.8.0
Requires-Dist: websockets>=13.0.1
Requires-Dist: wsproto>=1.2.0
Requires-Dist: PyYAML>=6.0
Requires-Dist: click>=8.0
Provides-Extra: dev
Requires-Dist: pytest>=6.0; extra == "dev"
Requires-Dist: pytest-cov>=2.0; extra == "dev"
Requires-Dist: black>=21.0; extra == "dev"
Requires-Dist: flake8>=3.8; extra == "dev"
Requires-Dist: mypy>=0.800; extra == "dev"
Requires-Dist: pre-commit>=2.0; extra == "dev"
Provides-Extra: cli
Requires-Dist: click>=8.0; extra == "cli"
Dynamic: author
Dynamic: home-page
Dynamic: license-file
Dynamic: requires-python
